rust_neighborlist-0.1.3.dist-info/METADATA
rust_neighborlist-0.1.3.dist-info/WHEEL
neighborlist/__init__.py
neighborlist/neighborlist.abi3.so
rust_neighborlist-0.1.3.dist-info/RECORD
