Metadata-Version: 2.1
Name: rust-neighborlist
Version: 0.1.3
Author: Mario Geiger <geiger.mario@gmail.com
Author-email: Mario Geiger <geiger.mario@gmail.com
